{
  "category": "Arrays 2D - Medium",
  "problems": [
    {
      "title": "Matrix Multiplication",
      "difficulty": "medium",
      "description": "Multiply two matrices and print the result.",
      "inputFormat": "First line: r1 c1 (first matrix dimensions)\nNext r1 lines: c1 integers each\nNext line: r2 c2 (second matrix dimensions)\nNext r2 lines: c2 integers each",
      "outputFormat": "Print the resulting matrix",
      "constraints": "1 ≤ r1, c1, r2, c2 ≤ 5\nc1 must equal r2",
      "sampleTestCases": [
        {
          "input": "2 2\n1 2\n3 4\n2 2\n5 6\n7 8",
          "output": "19 22\n43 50",
          "explanation": "Matrix multiplication result"
        }
      ],
      "hiddenTestCases": [
        {
          "input": "2 3\n1 2 3\n4 5 6\n3 2\n7 8\n9 10\n11 12",
          "output": "58 64\n139 154"
        }
      ],
      "points": 25,
      "starterCode": "#include <iostream>\nusing namespace std;\n\nint main() {\n    int r1, c1;\n    cin >> r1 >> c1;\n    \n    int a[10][10];\n    for(int i = 0; i < r1; i++) {\n        for(int j = 0; j < c1; j++) {\n            cin >> a[i][j];\n        }\n    }\n    \n    int r2, c2;\n    cin >> r2 >> c2;\n    \n    int b[10][10];\n    for(int i = 0; i < r2; i++) {\n        for(int j = 0; j < c2; j++) {\n            cin >> b[i][j];\n        }\n    }\n    \n    // Your code here\n    \n    return 0;\n}"
    },
    {
      "title": "Spiral Print",
      "difficulty": "medium",
      "description": "Print matrix elements in spiral order (clockwise).",
      "inputFormat": "First line: rows and columns (r c)\nNext r lines: c space-separated integers each",
      "outputFormat": "Print elements in spiral order, space-separated",
      "constraints": "1 ≤ r, c ≤ 5",
      "sampleTestCases": [
        {
          "input": "3 3\n1 2 3\n4 5 6\n7 8 9",
          "output": "1 2 3 6 9 8 7 4 5",
          "explanation": "Spiral: outer ring then inner"
        }
      ],
      "hiddenTestCases": [
        {
          "input": "2 2\n1 2\n3 4",
          "output": "1 2 4 3"
        }
      ],
      "points": 25,
      "starterCode": "#include <iostream>\nusing namespace std;\n\nint main() {\n    int r, c;\n    cin >> r >> c;\n    \n    int arr[10][10];\n    for(int i = 0; i < r; i++) {\n        for(int j = 0; j < c; j++) {\n            cin >> arr[i][j];\n        }\n    }\n    \n    // Your code here\n    \n    return 0;\n}"
    }
  ]
}